gyoza/__init__.py
gyoza/modelling/__init__.py
gyoza/modelling/flow_layers.py
gyoza/modelling/losses.py
gyoza/modelling/masks.py
gyoza/tutorials/__init__.py
gyoza/tutorials/data_synthesis.py
gyoza/tutorials/mathematics.py
gyoza/tutorials/modelling.py
gyoza/tutorials/plotting.py
gyoza/utilities/__init__.py
gyoza/utilities/tensors.py
gyoza-0.3.0.dist-info/licenses/LICENSE
gyoza-0.3.0.dist-info/METADATA
gyoza-0.3.0.dist-info/WHEEL
gyoza-0.3.0.dist-info/top_level.txt
gyoza-0.3.0.dist-info/RECORD
